k3s63/__init__.py
k3s63/date.py
k3s63/reset.py
k3s63-0.1.2.dist-info/LICENSE
k3s63-0.1.2.dist-info/METADATA
k3s63-0.1.2.dist-info/WHEEL
k3s63-0.1.2.dist-info/top_level.txt
k3s63-0.1.2.dist-info/RECORD
