Metadata-Version: 2.1
Name: k3s63
Version: 0.1.2
Summary: Toolkit by @k3s63 with date and reset functions
Home-page: https://pypi.org/project/k3s63/
Author: @k3s63
Author-email: k3s63c@gmail.com
Classifier: Programming Language :: Python :: 3
Classifier: License :: OSI Approved :: MIT License
Classifier: Operating System :: OS Independent
Requires-Python: >=3.6
License-File: LICENSE
